machine_learning_model_local/__init__.py
machine_learning_model_local/machine_learning_model.py
machine_learning_model_local-0.0.4.dist-info/METADATA
machine_learning_model_local-0.0.4.dist-info/WHEEL
machine_learning_model_local-0.0.4.dist-info/top_level.txt
machine_learning_model_local-0.0.4.dist-info/RECORD
