Metadata-Version: 2.1
Name: machine-learning-model-local
Version: 0.0.4
Summary: PyPI Package for Circles machine-learning-model-local Python
Home-page: https://github.com/circles-zone/machine-learning-model-local-python-package
Author: Circles
Author-email: info@circlez.ai
Classifier: Programming Language :: Python :: 3
Classifier: License :: Other/Proprietary License
Classifier: Operating System :: OS Independent
Requires-Dist: logger-local >=0.0.61
Requires-Dist: database-mysql-local >=0.0.290
